checkdmarc_signalless.py
checkdmarc_signalless-4.3.2.3.dist-info/LICENSE
checkdmarc_signalless-4.3.2.3.dist-info/METADATA
checkdmarc_signalless-4.3.2.3.dist-info/NOTICE
checkdmarc_signalless-4.3.2.3.dist-info/WHEEL
checkdmarc_signalless-4.3.2.3.dist-info/entry_points.txt
checkdmarc_signalless-4.3.2.3.dist-info/top_level.txt
checkdmarc_signalless-4.3.2.3.dist-info/RECORD
