Metadata-Version: 2.1
Name: checkdmarc-signalless
Version: 4.3.2.3
Summary: A Python module and command line parser for SPF and DMARC records
Home-page: https://github.com/DobroAlex/checkdmarc
Author: DobroAlex
Author-email: alexkoshernosiegov@gmail.com
License: Apache 2.0
Keywords: DNS,SPF,DMARC
Platform: UNKNOWN
Classifier: Development Status :: 5 - Production/Stable
Classifier: Intended Audience :: Developers
Classifier: Intended Audience :: Information Technology
Classifier: Operating System :: OS Independent
Classifier: License :: OSI Approved :: Apache Software License
Classifier: Programming Language :: Python :: 3 :: Only
Classifier: Programming Language :: Python :: 3
Classifier: Programming Language :: Python :: 3.6
Classifier: Programming Language :: Python :: 3.7
Classifier: Programming Language :: Python :: 3.8
Classifier: Programming Language :: Python :: 3.9
Requires-Dist: dnspython (>=2.0.0)
Requires-Dist: expiringdict (>=1.1.4)
Requires-Dist: pyleri (>=1.3.2)
Requires-Dist: publicsuffix2 (>=2.20191221)
Requires-Dist: requests (==2.24.0)
Requires-Dist: timeout-decorator (>=0.4.1)
